MANIFEST.in
README.md
setup.py
merge_closest/__init__.py
merge_closest.egg-info/PKG-INFO
merge_closest.egg-info/SOURCES.txt
merge_closest.egg-info/dependency_links.txt
merge_closest.egg-info/not-zip-safe
merge_closest.egg-info/requires.txt
merge_closest.egg-info/top_level.txt