Metadata-Version: 1.0
Name: merge-closest
Version: 0.1b160919-3
Summary: Merge two pandas DataFrames using closest match
Home-page: https://github.com/RobinFiveWords/merge_closest
Author: Robin Fishbein
Author-email: robinfishbein@yahoo.com
License: MIT
Keywords: pandas merge join closest approximate
Platform: UNKNOWN
